{
  "type": "Feature",
  "stac_version": "1.0.0",
  "id": "NAC_PHO_E041N1229_M1153417741L",
  "properties": {
    "datetime": "2014-04-29T13:34:34Z",
    "created": "2018-02-27T09:38:13.000",
    "start_datetime": "2014-04-29T13:34:34.000",
    "end_datetime": "2014-04-29T13:35:17.000",
    "platform": "LRO",
    "instruments": [
      "LROC"
    ],
    "gsd": 1.2,
    "ssys:targets": [
      "moon"
    ],
    "ssys:solar_longitude": 123.34678053602065,
    "processing:level": "5",
    "pdsode:ode_id": "23065754",
    "pdsode:pdsid": "NAC_PHO_E041N1229_M1153417741L",
    "pdsode:ihid": "LRO",
    "pdsode:iid": "LROC",
    "pdsode:pt": "SDRPHO",
    "pdsode:Data_Set_Id": "LRO-L-LROC-5-RDR-V1.0",
    "pdsode:PDSVolume_Id": "LROLRC_2001",
    "pdsode:RelativePathtoVol": "data\\sdp\\nac_pho\\e041n1229\\",
    "pdsode:LabelFileName": "nac_pho_e041n1229_m1153417741l.img",
    "pdsode:Product_creation_time": "2018-02-27T09:38:13.000",
    "pdsode:Target_name": "MOON",
    "pdsode:Product_version_id": "v1.0",
    "pdsode:Producer_id": "LRO_LROC_TEAM",
    "pdsode:Observation_time": "2014-04-29T13:34:55.500",
    "pdsode:SpaceCraft_clock_start_count": "N/A",
    "pdsode:SpaceCraft_clock_stop_count": "N/A",
    "pdsode:UTC_start_time": "2014-04-29T13:34:34.000",
    "pdsode:UTC_stop_time": "2014-04-29T13:35:17.000",
    "pdsode:Map_resolution": 25269.458686791,
    "pdsode:Map_scale": 1.2,
    "pdsode:Center_georeferenced": "True",
    "pdsode:Center_latitude": "4.2129",
    "pdsode:Center_longitude": "122.9178",
    "pdsode:BB_georeferenced": "True",
    "pdsode:Easternmost_longitude": "123.0465",
    "pdsode:Maximum_latitude": "5.0444",
    "pdsode:Minimum_latitude": "3.3814",
    "pdsode:Westernmost_longitude": "122.789",
    "pdsode:Footprint_geometry": "POLYGON ((122.789 3.3814, 122.789 4.3814, 122.789 5.0444, 123.0465 5.0444, 123.0465 4.0444, 123.0465 3.3814, 122.789 3.3814))",
    "pdsode:Footprint_C0_geometry": "POLYGON ((122.789 3.3814, 122.789 4.3814, 122.789 5.0444, 123.0465 5.0444, 123.0465 4.0444, 123.0465 3.3814, 122.789 3.3814))",
    "pdsode:Footprint_GL_geometry": "POLYGON ((122.789 3.3814, 122.789 4.3814, 122.789 5.0444, 123.0465 5.0444, 123.0465 4.0444, 123.0465 3.3814, 122.789 3.3814))",
    "pdsode:Footprint_NP_geometry": "MULTIPOLYGON EMPTY",
    "pdsode:Footprint_SP_geometry": "MULTIPOLYGON EMPTY",
    "pdsode:Footprints_cross_meridian": "False",
    "pdsode:Pole_state": "none",
    "pdsode:Footprint_souce": "PDS Label Map Projection Bounding Box",
    "pdsode:Description": "\"King Crater Ejecta four band map-projected NAC photometric product from M1153417741L. Band 1 is I/F, Bands 2-4 are backplanes for Phase, Emission, and Incidence, respectively. For more info see [MARTINETAL2018]\"",
    "pdsode:External_url": "https://pds.lroc.asu.edu/data/LRO-L-LROC-5-RDR-V1.0/LROLRC_2001/DATA/SDP/NAC_PHO/E041N1229/NAC_PHO_E041N1229_M1153417741L.IMG",
    "pdsode:FilesURL": "https://ode.rsl.wustl.edu/moon/productfiles.aspx?product_id=NAC_PHO_E041N1229_M1153417741L&product_idGeo=23065754",
    "pdsode:ProductURL": "https://ode.rsl.wustl.edu/moon/indexproductpage.aspx?product_id=NAC_PHO_E041N1229_M1153417741L&product_idGeo=23065754",
    "pdsode:LabelURL": "https://pds.lroc.asu.edu/data/LRO-L-LROC-5-RDR-V1.0/LROLRC_2001/DATA/SDP/NAC_PHO/E041N1229/NAC_PHO_E041N1229_M1153417741L.IMG"
  },
  "geometry": {
    "type": "Polygon",
    "coordinates": [
      [
        [
          122.789,
          3.3814
        ],
        [
          122.789,
          4.3814
        ],
        [
          122.789,
          5.0444
        ],
        [
          123.0465,
          5.0444
        ],
        [
          123.0465,
          4.0444
        ],
        [
          123.0465,
          3.3814
        ],
        [
          122.789,
          3.3814
        ]
      ]
    ]
  },
  "links": [
    {
      "rel": "root",
      "href": "../../catalog.json",
      "type": "application/json",
      "title": "Moon STAC Catalog holding one or several PDSSP-compliant data products collections."
    },
    {
      "rel": "collection",
      "href": "../collection.json",
      "type": "application/json",
      "title": "LRO/LROC Special Data Products - Map projected NAC photometric product"
    },
    {
      "rel": "parent",
      "href": "../collection.json",
      "type": "application/json",
      "title": "LRO/LROC Special Data Products - Map projected NAC photometric product"
    }
  ],
  "assets": {
    "DSMAP.CAT": {
      "href": "https://pds.lroc.asu.edu/data/LRO-L-LROC-5-RDR-V1.0/LROLRC_2001/CATALOG/DSMAP.CAT",
      "type": "",
      "title": "DSMAP.CAT",
      "description": "MAP PROJECTION FILE",
      "roles": [
        "Referenced"
      ]
    },
    "NAC_PHO_E041N1229_IMAGES.TXT": {
      "href": "https://pds.lroc.asu.edu/data/LRO-L-LROC-5-RDR-V1.0/LROLRC_2001/DATA/SDP/NAC_PHO/E041N1229/NAC_PHO_E041N1229_IMAGES.TXT",
      "type": "",
      "title": "NAC_PHO_E041N1229_IMAGES.TXT",
      "description": "IMAGE LIST",
      "roles": [
        "Referenced"
      ]
    },
    "NAC_PHO_E041N1229_M1153417741L.BROWSE.PNG": {
      "href": "https://pds.lroc.asu.edu/data/LRO-L-LROC-5-RDR-V1.0/LROLRC_2001/EXTRAS/BROWSE/NAC_PHO/E041N1229/NAC_PHO_E041N1229_M1153417741L.BROWSE.PNG",
      "type": "image/png",
      "title": "NAC_PHO_E041N1229_M1153417741L.BROWSE.PNG",
      "description": "BROWSE PNG IMAGE",
      "roles": [
        "thumbnail"
      ]
    },
    "NAC_PHO_E041N1229_M1153417741L.IMG": {
      "href": "https://pds.lroc.asu.edu/data/LRO-L-LROC-5-RDR-V1.0/LROLRC_2001/DATA/SDP/NAC_PHO/E041N1229/NAC_PHO_E041N1229_M1153417741L.IMG",
      "type": "",
      "title": "NAC_PHO_E041N1229_M1153417741L.IMG",
      "description": "PRODUCT DATA FILE WITH LABEL",
      "roles": [
        "data"
      ]
    },
    "NAC_PHO_E041N1229_M1153417741L.MASK.TIF": {
      "href": "https://pds.lroc.asu.edu/data/LRO-L-LROC-5-RDR-V1.0/LROLRC_2001/EXTRAS/BROWSE/NAC_PHO/E041N1229/NAC_PHO_E041N1229_M1153417741L.MASK.TIF",
      "type": "",
      "title": "NAC_PHO_E041N1229_M1153417741L.MASK.TIF",
      "description": "MASK IMAGE",
      "roles": [
        "thumbnail"
      ]
    },
    "NAC_PHO_E041N1229_M1153417741L.PYR.TIF": {
      "href": "https://pds.lroc.asu.edu/data/LRO-L-LROC-5-RDR-V1.0/LROLRC_2001/EXTRAS/BROWSE/NAC_PHO/E041N1229/NAC_PHO_E041N1229_M1153417741L.PYR.TIF",
      "type": "",
      "title": "NAC_PHO_E041N1229_M1153417741L.PYR.TIF",
      "description": "BROWSE TIF IMAGE",
      "roles": [
        "thumbnail"
      ]
    },
    "NAC_PHO_E041N1229_M1153417741L.TIF": {
      "href": "https://pds.lroc.asu.edu/data/LRO-L-LROC-5-RDR-V1.0/LROLRC_2001/EXTRAS/BROWSE/NAC_PHO/E041N1229/NAC_PHO_E041N1229_M1153417741L.TIF",
      "type": "",
      "title": "NAC_PHO_E041N1229_M1153417741L.TIF",
      "description": "FULL BROWSE IMAGE",
      "roles": [
        "thumbnail"
      ]
    },
    "NAC_PHO_E041N1229_M1153417741L_IMG.KML": {
      "href": "https://ode.rsl.wustl.edu/moon/datafile/kmlfiles/lro-l-lroc-5-rdr-v1/lrolrc_2001/data/sdp/nac_pho/e041n1229/nac_pho_e041n1229_m1153417741l_img.kml",
      "type": "",
      "title": "NAC_PHO_E041N1229_M1153417741L_IMG.KML",
      "description": "PRODUCT KML FILE <A HREF=\"PAGEHELP/CONTENT/FREQUENTLY_ASKED_QUESTIONS/PRODUCT_FOOTPRINTS.HTM\" TARGET=\"_BLANK\">HELP</A>",
      "roles": [
        "Derived"
      ]
    },
    "NAC_PHO_E041N1229_M1153417741L_IMG.TAR.GZ": {
      "href": "https://ode.rsl.wustl.edu/moon/datafile/shapefiles/lro-l-lroc-5-rdr-v1/lrolrc_2001/data/sdp/nac_pho/e041n1229/nac_pho_e041n1229_m1153417741l_img.tar.gz",
      "type": "",
      "title": "NAC_PHO_E041N1229_M1153417741L_IMG.TAR.GZ",
      "description": "PRODUCT FOOTPRINT SHAPEFILES (TAR.GZ) <A HREF=\"PAGEHELP/CONTENT/FREQUENTLY_ASKED_QUESTIONS/PRODUCT_FOOTPRINTS.HTM\" TARGET=\"_BLANK\">HELP</A>",
      "roles": [
        "Derived"
      ]
    },
    "NAC_PHO_E041N1229_M1153417741L_IMG.ZIP": {
      "href": "https://ode.rsl.wustl.edu/moon/datafile/shapefiles/lro-l-lroc-5-rdr-v1/lrolrc_2001/data/sdp/nac_pho/e041n1229/nac_pho_e041n1229_m1153417741l_img.zip",
      "type": "",
      "title": "NAC_PHO_E041N1229_M1153417741L_IMG.ZIP",
      "description": "PRODUCT FOOTPRINT SHAPEFILES (ZIP) <A HREF=\"PAGEHELP/CONTENT/FREQUENTLY_ASKED_QUESTIONS/PRODUCT_FOOTPRINTS.HTM\" TARGET=\"_BLANK\">HELP</A>",
      "roles": [
        "Derived"
      ]
    },
    "NAC_PHO_E041N1229_README.TXT": {
      "href": "https://pds.lroc.asu.edu/data/LRO-L-LROC-5-RDR-V1.0/LROLRC_2001/DATA/SDP/NAC_PHO/E041N1229/NAC_PHO_E041N1229_README.TXT",
      "type": "",
      "title": "NAC_PHO_E041N1229_README.TXT",
      "description": "README INFORMATION",
      "roles": [
        "Referenced"
      ]
    }
  },
  "bbox": [
    122.789,
    3.3814,
    123.0465,
    5.0444
  ],
  "stac_extensions": [
    "ssys",
    "processing"
  ],
  "collection": "LRO_LROC_SDRPHO"
}